mogrifier/__init__.py
mogrifier/mogrifier.py
mogrifier-0.0.5.dist-info/LICENSE
mogrifier-0.0.5.dist-info/METADATA
mogrifier-0.0.5.dist-info/WHEEL
mogrifier-0.0.5.dist-info/top_level.txt
mogrifier-0.0.5.dist-info/RECORD
