Metadata-Version: 2.1
Name: mogrifier
Version: 0.0.5
Summary: Implementation of Mogrifier circuit from Deepmind
Home-page: https://github.com/lucidrains/mogrifier
Author: Phil Wang
Author-email: lucidrains@gmail.com
License: MIT
Keywords: artificial intelligence,natural language processing,improved conditioning
Classifier: Development Status :: 4 - Beta
Classifier: Intended Audience :: Developers
Classifier: Topic :: Scientific/Engineering :: Artificial Intelligence
Classifier: License :: OSI Approved :: MIT License
Classifier: Programming Language :: Python :: 3.6
License-File: LICENSE
Requires-Dist: einops >=0.8
Requires-Dist: torch
